Metadata-Version: 1.0
Name: myFirstpythonlibrary00
Version: 0.1.0
Summary: my first python library
Home-page: UNKNOWN
Author: Me
Author-email: UNKNOWN
License: MIT
Platform: UNKNOWN
